{"list":{"ListName":"WYNIKI|01-WYNIKI KLASYFIKACJI GENERALNEJ","BottomPicture":"","BottomPictureShow":0,"ColumnHeadsFontName":"","ColumnHeadsFontSize":9,"ColumnHeadsFontBold":true,"ColumnHeadsFontItalic":false,"ColumnHeadsFontUnderlined":false,"ColumnHeadsColor":"","ColumnHeadsShow":2,"Columns":1,"ColumnSpacing":5,"CoverSheet":"","BackSheet":"","Design":"","DesignShow":2,"EveryOtherLineGray":true,"FontName":"Arial","FontSize":7,"FooterFontName":"","FooterFontSize":10,"FooterFontBold":false,"FooterFontItalic":false,"FooterFontUnderlined":false,"FooterColor":"","GrayLine":true,"HeadLine1":"XII Memoriał im. Czesława Wasielewskiego 2026 - ","HeadLine1FontName":"","HeadLine1FontSize":16,"HeadLine1FontBold":false,"HeadLine1FontItalic":false,"HeadLine1FontUnderlined":true,"HeadLine2":"Brześć Kujawski 2026-05-23","HeadLine1Color":"","HeadLine1Show":2,"HeadLine2FontName":"","HeadLine2FontSize":16,"HeadLine2FontBold":true,"HeadLine2FontItalic":false,"HeadLine2FontUnderlined":false,"HeadLine2Color":"","HeadLine2Show":2,"HeightBottomPicture":10,"LineColor":"","LineBackColor":"","LineDynamicFormat":"iif([POSITION]%2;\"BG(#ebebeb)\")","LineSpacing":1,"MaxRecords":0,"MultiplierField":"","PageFormat":0,"PageMarginBottom":5,"PageMarginLeft":5,"PageMarginRight":5,"PageMarginTop":5,"PageSize":2,"PageHeight":420,"PageWidth":297,"SepLine":true,"TopRightPicture":"FOXTER_Sport_LOGO_mini.jpg","TopRightPictureShow":2,"ListHeaderText":"","ListFooterText":"Liczba zawodników: 319","ListHeaderFooterFontName":"","ListHeaderFooterFontSize":10,"ListHeaderFooterFontBold":false,"ListHeaderFooterFontItalic":false,"ListHeaderFooterFontUnderlined":false,"ListHeaderFooterAlignment":1,"Remarks":"","LastChange":"2026-05-09 17:16:43","FooterText1":"[EVENTINFOTEXT1]\n[EVENTINFOTEXT2]","FooterText2":"\n[page]","FooterText3":"Profesjonalny pomiar czasu - FOXTER SPORT\nkontakt@foxter-sport.pl","Orders":[{"Expression":"CONTEST","Descending":false,"Grouping":0,"GroupFilterDefault":1,"GroupFilterLabel":"","PageBreak":0,"FontName":"","FontSize":12,"FontBold":true,"FontItalic":false,"FontUnderlined":false,"Color":"","BackgroundColor":"","Spacing":2},{"Expression":"CONTEST.NAME","Descending":false,"Grouping":2,"GroupFilterDefault":0,"GroupFilterLabel":"Dystans","PageBreak":4,"FontName":"","FontSize":12,"FontBold":true,"FontItalic":false,"FontUnderlined":false,"Color":"","BackgroundColor":"#92C7D6","Spacing":2},{"Expression":"GenderMF_long","Descending":false,"Grouping":3,"GroupFilterDefault":2,"GroupFilterLabel":"Płeć","PageBreak":0,"FontName":"","FontSize":12,"FontBold":false,"FontItalic":false,"FontUnderlined":false,"Color":"","BackgroundColor":"","Spacing":0},{"Expression":"AGEGROUP.OrderPos","Descending":false,"Grouping":0,"GroupFilterDefault":1,"GroupFilterLabel":"","PageBreak":0,"FontName":"","FontSize":12,"FontBold":false,"FontItalic":false,"FontUnderlined":false,"Color":"","BackgroundColor":"","Spacing":0},{"Expression":"AGEGROUP.NAME","Descending":false,"Grouping":3,"GroupFilterDefault":2,"GroupFilterLabel":"Kategoria wiekowa","PageBreak":0,"FontName":"","FontSize":12,"FontBold":false,"FontItalic":false,"FontUnderlined":false,"Color":"","BackgroundColor":"","Spacing":2},{"Expression":"STATUS","Descending":false,"Grouping":0,"GroupFilterDefault":1,"GroupFilterLabel":"","PageBreak":0,"FontName":"","FontSize":12,"FontBold":false,"FontItalic":false,"FontUnderlined":false,"Color":"","BackgroundColor":"","Spacing":0},{"Expression":"OverallRank","Descending":false,"Grouping":0,"GroupFilterDefault":1,"GroupFilterLabel":"","PageBreak":0,"FontName":"","FontSize":12,"FontBold":false,"FontItalic":false,"FontUnderlined":false,"Color":"","BackgroundColor":"","Spacing":0}],"Filters":[{"OrConjunction":false,"Expression1":"OverallRank","Operator":"\u003e","Expression2":"0"},{"OrConjunction":true,"Expression1":"STATUS","Operator":"\u003e","Expression2":"0"}],"Fields":[{"Expression":"AUTORANK","Label":"","Label2":"","Alignment":1,"FontBold":false,"FontItalic":false,"FontUnderlined":false,"Line":1,"Color":"","Link":"","ColSpan":0,"ColOffset":0,"Position":0,"DynamicFormat":"","PreviewOnly":false,"ResponsiveHide":0},{"Expression":"BIB","Label":"Nr.","Label2":"","Alignment":1,"FontBold":true,"FontItalic":true,"FontUnderlined":false,"Line":1,"Color":"","Link":"","ColSpan":0,"ColOffset":0,"Position":0,"DynamicFormat":"","PreviewOnly":false,"ResponsiveHide":0},{"Expression":"COUNTRY.FLAG","Label":"","Label2":"","Alignment":1,"FontBold":false,"FontItalic":false,"FontUnderlined":false,"Line":1,"Color":"","Link":"","ColSpan":0,"ColOffset":0,"Position":0,"DynamicFormat":"","PreviewOnly":false,"ResponsiveHide":0},{"Expression":"CorrectSpelling([DisplayName])","Label":"Imię i nazwisko","Label2":"","Alignment":1,"FontBold":true,"FontItalic":false,"FontUnderlined":false,"Line":1,"Color":"","Link":"","ColSpan":0,"ColOffset":0,"Position":0,"DynamicFormat":"if([SEX]=\"f\";\"C(#d115b8)\";)","PreviewOnly":false,"ResponsiveHide":0},{"Expression":"[CLUB] \u0026 \" (\" \u0026 [CITY] \u0026 \")\" ","Label":"Klub","Label2":"","Alignment":1,"FontBold":false,"FontItalic":false,"FontUnderlined":false,"Line":1,"Color":"","Link":"","ColSpan":0,"ColOffset":0,"Position":0,"DynamicFormat":"","PreviewOnly":false,"ResponsiveHide":0},{"Expression":"\"I\"","Label":"","Label2":"","Alignment":1,"FontBold":false,"FontItalic":false,"FontUnderlined":false,"Line":1,"Color":"","Link":"","ColSpan":0,"ColOffset":0,"Position":0,"DynamicFormat":"","PreviewOnly":false,"ResponsiveHide":0},{"Expression":"OverallRank","Label":"OPEN","Label2":"","Alignment":2,"FontBold":false,"FontItalic":false,"FontUnderlined":false,"Line":1,"Color":"","Link":"","ColSpan":0,"ColOffset":0,"Position":0,"DynamicFormat":"","PreviewOnly":false,"ResponsiveHide":0},{"Expression":"\"I\"","Label":"","Label2":"","Alignment":1,"FontBold":false,"FontItalic":false,"FontUnderlined":false,"Line":1,"Color":"","Link":"","ColSpan":0,"ColOffset":0,"Position":0,"DynamicFormat":"","PreviewOnly":false,"ResponsiveHide":0},{"Expression":"GenderMF","Label":"Płeć","Label2":"","Alignment":2,"FontBold":false,"FontItalic":false,"FontUnderlined":false,"Line":1,"Color":"","Link":"","ColSpan":0,"ColOffset":0,"Position":0,"DynamicFormat":"if([SEX]=\"f\";\"C(#d115b8);B\")","PreviewOnly":false,"ResponsiveHide":0},{"Expression":"medal([GenderRank])","Label":"","Label2":"","Alignment":2,"FontBold":false,"FontItalic":false,"FontUnderlined":false,"Line":1,"Color":"","Link":"","ColSpan":0,"ColOffset":0,"Position":0,"DynamicFormat":"","PreviewOnly":false,"ResponsiveHide":0},{"Expression":"[GenderRankp]","Label":"M","Label2":"","Alignment":2,"FontBold":false,"FontItalic":false,"FontUnderlined":false,"Line":1,"Color":"","Link":"","ColSpan":0,"ColOffset":0,"Position":0,"DynamicFormat":"","PreviewOnly":false,"ResponsiveHide":0},{"Expression":"\"(\"","Label":"","Label2":"","Alignment":1,"FontBold":false,"FontItalic":false,"FontUnderlined":false,"Line":1,"Color":"","Link":"","ColSpan":0,"ColOffset":0,"Position":0,"DynamicFormat":"","PreviewOnly":false,"ResponsiveHide":0},{"Expression":"[AGEGROUP1.NAME]","Label":"Kat. wiek.","Label2":"","Alignment":1,"FontBold":false,"FontItalic":false,"FontUnderlined":false,"Line":1,"Color":"","Link":"","ColSpan":0,"ColOffset":0,"Position":0,"DynamicFormat":"if([SEX]=\"f\";\"C(#d115b8);B\")","PreviewOnly":false,"ResponsiveHide":0},{"Expression":"medal([AGRank])","Label":"","Label2":"","Alignment":2,"FontBold":false,"FontItalic":false,"FontUnderlined":false,"Line":1,"Color":"","Link":"","ColSpan":0,"ColOffset":0,"Position":0,"DynamicFormat":"","PreviewOnly":false,"ResponsiveHide":0},{"Expression":"if([GenderRank]\u003c=[DecorationDepth];\"OPEN\"; if([AGRank]\u003e0;[AGRank]))","Label":"","Label2":"","Alignment":2,"FontBold":false,"FontItalic":false,"FontUnderlined":false,"Line":1,"Color":"","Link":"","ColSpan":0,"ColOffset":0,"Position":0,"DynamicFormat":"","PreviewOnly":false,"ResponsiveHide":0},{"Expression":"\")\"","Label":"","Label2":"","Alignment":1,"FontBold":false,"FontItalic":false,"FontUnderlined":false,"Line":1,"Color":"","Link":"","ColSpan":0,"ColOffset":0,"Position":0,"DynamicFormat":"","PreviewOnly":false,"ResponsiveHide":0},{"Expression":"wyniki_kategorie_dodatkowe","Label":"kat. dodatkowe","Label2":"","Alignment":3,"FontBold":false,"FontItalic":false,"FontUnderlined":false,"Line":1,"Color":"","Link":"","ColSpan":0,"ColOffset":0,"Position":0,"DynamicFormat":"","PreviewOnly":false,"ResponsiveHide":0},{"Expression":"\"I\"","Label":"","Label2":"","Alignment":1,"FontBold":false,"FontItalic":false,"FontUnderlined":false,"Line":1,"Color":"","Link":"","ColSpan":0,"ColOffset":0,"Position":0,"DynamicFormat":"","PreviewOnly":false,"ResponsiveHide":0},{"Expression":"[finish.CHIP.PACE] \u0026 \" min/km\"","Label":"tempo","Label2":"","Alignment":1,"FontBold":false,"FontItalic":false,"FontUnderlined":false,"Line":1,"Color":"","Link":"","ColSpan":0,"ColOffset":0,"Position":0,"DynamicFormat":"","PreviewOnly":false,"ResponsiveHide":0},{"Expression":"Finish.CHIP","Label":"Netto","Label2":"","Alignment":1,"FontBold":false,"FontItalic":false,"FontUnderlined":false,"Line":1,"Color":"","Link":"","ColSpan":0,"ColOffset":0,"Position":0,"DynamicFormat":"if([GunRank]\u003e[GunRankDepth];\"B\";\"C(#d115b8)\")","PreviewOnly":false,"ResponsiveHide":0},{"Expression":"Finish.GUN","Label":"Brutto","Label2":"","Alignment":1,"FontBold":false,"FontItalic":false,"FontUnderlined":false,"Line":1,"Color":"","Link":"","ColSpan":0,"ColOffset":0,"Position":0,"DynamicFormat":"if([GunRank]\u003c=[GunRankDepth];\"B\";\"C(#d115b8)\")","PreviewOnly":false,"ResponsiveHide":0},{"Expression":"kara_text","Label":"kara","Label2":"","Alignment":1,"FontBold":false,"FontItalic":false,"FontUnderlined":false,"Line":1,"Color":"","Link":"","ColSpan":0,"ColOffset":0,"Position":0,"DynamicFormat":"","PreviewOnly":false,"ResponsiveHide":0},{"Expression":"\"I\"","Label":"","Label2":"","Alignment":1,"FontBold":false,"FontItalic":false,"FontUnderlined":false,"Line":1,"Color":"","Link":"","ColSpan":0,"ColOffset":0,"Position":0,"DynamicFormat":"","PreviewOnly":false,"ResponsiveHide":0},{"Expression":"TimeorStatus","Label":"Wynik","Label2":"","Alignment":1,"FontBold":false,"FontItalic":false,"FontUnderlined":false,"Line":1,"Color":"","Link":"","ColSpan":0,"ColOffset":0,"Position":0,"DynamicFormat":"","PreviewOnly":false,"ResponsiveHide":-1},{"Expression":"\"I\"","Label":"","Label2":"","Alignment":1,"FontBold":false,"FontItalic":false,"FontUnderlined":false,"Line":1,"Color":"","Link":"","ColSpan":0,"ColOffset":0,"Position":0,"DynamicFormat":"","PreviewOnly":false,"ResponsiveHide":0}],"SelectorResults":[]},"data":[["178","180","1","[img:/graphics/flags/PL.svg]","Tomaszewski Maciej","GKS FABIANKI (Torun)","I","1","M","[img:medal1.png|height:15px]","1.","(","M30-39","","OPEN",")","","3:20 min/km","0:33:23","0:33:23","","0:33:23","BG(#ebebeb)","","","C(#d115b8)","B"],["192","351","2","[img:/graphics/flags/PL.svg]","Ratajczyk Przemysław","TKKF Kolejarz Bydgoszcz (Aleksandrów Kujawski)","I","2","M","[img:medal2.png|height:15px]","2.","(","M30-39","","OPEN",")","","3:22 min/km","0:33:41","0:33:42","","0:33:42","","","","C(#d115b8)","B"],["177","353","3","[img:/graphics/flags/PL.svg]","Tomaszewski Milosz","GKS FABIANKI (Toruń)","I","3","M","[img:medal3.png|height:15px]","3.","(","M30-39","","OPEN",")","","3:27 min/km","0:34:34","0:34:34","","0:34:34","BG(#ebebeb)","","","C(#d115b8)","B"],["26","28","4","[img:/graphics/flags/PL.svg]","Kunecki Dariusz","KUNA Team Włocławek (Włocławek)","I","4","M","","4.","(","M40-49","[img:medal1.png|height:15px]","1",")","","3:31 min/km","0:35:14","0:35:14","","0:35:14","","","","C(#d115b8)","B"],["57","59","5","[img:/graphics/flags/PL.svg]","Piasecki Krzysztof","KUNA Team Włocławek (Włocławek)","I","5","M","","5.","(","M30-39","[img:medal1.png|height:15px]","1",")","","3:31 min/km","0:35:14","0:35:14","","0:35:14","BG(#ebebeb)","","","C(#d115b8)","B"],["60","62","6","[img:/graphics/flags/PL.svg]","Pasternak Robert","KUNA Team Włocławek (Włocławek)","I","6","M","","6.","(","M40-49","[img:medal2.png|height:15px]","2",")","","3:38 min/km","0:36:20","0:36:20","","0:36:20","","","","C(#d115b8)","B"],["71","73","7","[img:/graphics/flags/PL.svg]","Grzegocki Piotr","SamiSwoi (Strzelno)","I","7","M","","7.","(","M30-39","[img:medal2.png|height:15px]","2",")","","3:39 min/km","0:36:33","0:36:34","","0:36:34","BG(#ebebeb)","","","C(#d115b8)","B"],["333","359","8","[img:/graphics/flags/PL.svg]","Dzięgiel-Poślada Andżelika","GKS Fabianki (Toruń)","I","8","K","[img:medal1.png|height:15px]","1.","(","K30-39","","OPEN",")","","3:39 min/km","0:36:39","0:36:39","","0:36:39","","C(#d115b8)","C(#d115b8);B","C(#d115b8)","B"],["89","91","9","[img:/graphics/flags/PL.svg]","Grudziński Maciej","WKB MARATOŃCZYK WŁOCŁAWEK (Włocławek)","I","9","M","","8.","(","M40-49","[img:medal3.png|height:15px]","3",")","kat.Lubraniec (1M)","3:40 min/km","0:36:45","0:36:45","","0:36:45","BG(#ebebeb)","","","C(#d115b8)","B"],["200","202","10","[img:/graphics/flags/PL.svg]","Pietrzak Michał","KUNA  Team Włocławek (Włocławk)","I","10","M","","9.","(","M20-29","[img:medal1.png|height:15px]","1",")","","3:43 min/km","0:37:11","0:37:12","","0:37:12","","","","C(#d115b8)","B"],["151","352","11","[img:/graphics/flags/PL.svg]","Rogoziński Dawid","Teamochal (Bydgoszcz)","I","11","M","","10.","(","M30-39","[img:medal3.png|height:15px]","3",")","","3:45 min/km","0:37:33","0:37:33","","0:37:33","BG(#ebebeb)","","","C(#d115b8)","B"],["210","212","12","[img:/graphics/flags/PL.svg]","Donarski Bartek","Biegaj z Dymkiem (Płock)","I","12","M","","11.","(","M20-29","[img:medal2.png|height:15px]","2",")","","3:45 min/km","0:37:37","0:37:38","","0:37:38","","","","C(#d115b8)","B"],["118","120","13","[img:/graphics/flags/PL.svg]","Komorowski Tomasz","WKB Maratończyk Włocławek (Wloclawek)","I","13","M","","12.","(","M40-49","","4",")","","3:46 min/km","0:37:40","0:37:42","","0:37:42","BG(#ebebeb)","","","C(#d115b8)","B"],["18","20","14","[img:/graphics/flags/PL.svg]","Jagodziński Piotr","WKB Maratończyk Włocławek (Włocławek)","I","14","M","","13.","(","M30-39","","4",")","","3:46 min/km","0:37:44","0:37:44","","0:37:44","","","","C(#d115b8)","B"],["68","70","15","[img:/graphics/flags/PL.svg]","Kalota Joanna","GKS FABIANKI (Toruń)","I","15","K","[img:medal2.png|height:15px]","2.","(","K30-39","","OPEN",")","","3:47 min/km","0:37:58","0:37:58","","0:37:58","BG(#ebebeb)","C(#d115b8)","C(#d115b8);B","C(#d115b8)","B"],["123","125","16","[img:/graphics/flags/PL.svg]","Grzegocki Mateusz","SamiSwoi (Borkowo)","I","16","M","","14.","(","M30-39","","5",")","","3:50 min/km","0:38:29","0:38:30","","0:38:30","","","","C(#d115b8)","B"],["39","41","17","[img:/graphics/flags/PL.svg]","Wojciechowski Przemysław","parkrun Toruń (Toruń)","I","17","M","","15.","(","M40-49","","5",")","","3:56 min/km","0:39:24","0:39:25","","0:39:25","BG(#ebebeb)","","","C(#d115b8)","B"],["143","145","18","[img:/graphics/flags/PL.svg]","Kiprijanovski Wiktoria","Kujawsko-Pomorskie (Torun)","I","18","K","[img:medal3.png|height:15px]","3.","(","K20-29","","OPEN",")","","3:56 min/km","0:39:29","0:39:31","","0:39:31","","C(#d115b8)","C(#d115b8);B","C(#d115b8)","B"],["56","58","19","[img:/graphics/flags/PL.svg]","Mrówczyński Wojciech","Rozbiegani Lubraniec (Lubraniec)","I","19","M","","16.","(","M40-49","","6",")","kat.Lubraniec (2M)","3:58 min/km","0:39:48","0:39:49","","0:39:49","BG(#ebebeb)","","","C(#d115b8)","B"],["83","85","20","[img:/graphics/flags/PL.svg]","Woźniak Michał"," (Chodecz)","I","20","M","","17.","(","M40-49","","7",")","","3:58 min/km","0:39:47","0:39:51","","0:39:51","","","","C(#d115b8)","B"],["167","169","21","[img:/graphics/flags/PL.svg]","Ozdoba Krystian","TRITON KONIN (Ostrowite)","I","21","M","","18.","(","M20-29","[img:medal3.png|height:15px]","3",")","","3:59 min/km","0:39:53","0:39:54","","0:39:54","BG(#ebebeb)","","","C(#d115b8)","B"],["145","147","22","[img:/graphics/flags/PL.svg]","Maciaszek Krzysztof","Kujawsko-Pomorskie (Toruń)","I","22","M","","19.","(","M40-49","","8",")","","4:00 min/km","0:40:09","0:40:11","","0:40:11","","","","C(#d115b8)","B"],["28","30","23","[img:/graphics/flags/PL.svg]","Majewski Waldemar","KUNA Team Włocławek (Włocławek)","I","23","M","","20.","(","M40-49","","9",")","","4:01 min/km","0:40:13","0:40:15","","0:40:15","BG(#ebebeb)","","","C(#d115b8)","B"],["3","5","24","[img:/graphics/flags/PL.svg]","Łęgosz Piotr","KM PSP Toruń (Złotoria)","I","24","M","","21.","(","M40-49","","10",")","","4:04 min/km","0:40:41","0:40:48","","0:40:48","","","","C(#d115b8)","B"],["146","148","25","[img:/graphics/flags/PL.svg]","Pilarski Krzysztof","Kujawsko-Pomorskie (Toruń)","I","25","M","","22.","(","M40-49","","11",")","","4:05 min/km","0:40:50","0:40:52","","0:40:52","BG(#ebebeb)","","","C(#d115b8)","B"],["111","113","26","[img:/graphics/flags/PL.svg]","Woźniak Sylwester"," (Brześć Kujawski)","I","26","M","","23.","(","M20-29","","4",")","kat. Brześć K. (1M) ","4:05 min/km","0:40:56","0:40:59","","0:40:59","","","","C(#d115b8)","B"],["128","130","27","[img:/graphics/flags/PL.svg]","Wawrzynowicz Sylwester","Parkrun Toruń (Toruń)","I","27","M","","24.","(","M40-49","","12",")","","4:06 min/km","0:41:06","0:41:08","","0:41:08","BG(#ebebeb)","","","C(#d115b8)","B"],["162","164","28","[img:/graphics/flags/PL.svg]","Stawski Andżelo","Biegowi Przyjaciele (Ciechocinek)","I","28","M","","25.","(","M30-39","","6",")","","4:07 min/km","0:41:15","0:41:15","","0:41:15","","","","C(#d115b8)","B"],["55","57","29","[img:/graphics/flags/PL.svg]","Majerski Przemysław","ROZBIEGANI LUBRANIEC (Lubraniec)","I","29","M","","26.","(","M30-39","","7",")","kat.Lubraniec (3M)","4:07 min/km","0:41:16","0:41:18","","0:41:18","BG(#ebebeb)","","","C(#d115b8)","B"],["176","178","30","[img:/graphics/flags/PL.svg]","Żuchowski Jozef"," (Radomin)","I","30","M","","27.","(","M50-59","[img:medal1.png|height:15px]","1",")","","4:07 min/km","0:41:16","0:41:19","","0:41:19","","","","C(#d115b8)","B"],["51","53","31","[img:/graphics/flags/PL.svg]","Lewandowski Maciej"," (Lubraniec)","I","31","M","","28.","(","M20-29","","5",")","kat.Lubraniec (4M)","4:08 min/km","0:41:21","0:41:22","","0:41:21","BG(#ebebeb)","","","B","C(#d115b8)"],["2","4","32","[img:/graphics/flags/PL.svg]","Rok-Szpala Sylwia","Parkrun Toruń (Lubicz Górny)","I","32","K","","4.","(","K40-49","[img:medal1.png|height:15px]","1",")","","4:08 min/km","0:41:21","0:41:23","","0:41:21","","C(#d115b8)","C(#d115b8);B","B","C(#d115b8)"],["53","55","33","[img:/graphics/flags/PL.svg]","Bińczarski Patryk","WKB MARATOŃCZYK WŁOCŁAWEK (Włocławek)","I","33","M","","29.","(","M40-49","","13",")","","4:09 min/km","0:41:31","0:41:32","","0:41:31","BG(#ebebeb)","","","B","C(#d115b8)"],["99","101","34","[img:/graphics/flags/PL.svg]","Czerwiński Mikołaj"," (Brześć Kujawski)","I","34","M","","30.","(","M16-19","[img:medal1.png|height:15px]","1",")","kat. Brześć K. (2M) ","4:10 min/km","0:41:48","0:41:57","","0:41:48","","","","B","C(#d115b8)"],["147","149","35","[img:/graphics/flags/PL.svg]","Przybylski Patryk","Kujawsko-Pomorskie (Toruń)","I","35","M","","31.","(","M40-49","","14",")","","4:11 min/km","0:41:52","0:41:55","","0:41:52","BG(#ebebeb)","","","B","C(#d115b8)"],["79","81","36","[img:/graphics/flags/PL.svg]","Frąk Edyta","parkrun Toruń (Toruń)","I","36","K","","5.","(","K30-39","[img:medal1.png|height:15px]","1",")","","4:12 min/km","0:42:05","0:42:08","","0:42:05","","C(#d115b8)","C(#d115b8);B","B","C(#d115b8)"],["163","165","37","[img:/graphics/flags/PL.svg]","Hussein Abdalla","parkrun Toruń (Konradowo)","I","37","M","","32.","(","M30-39","","8",")","","4:13 min/km","0:42:17","0:42:21","","0:42:17","BG(#ebebeb)","","","B","C(#d115b8)"],["77","79","38","[img:/graphics/flags/PL.svg]","Bołkowiec Tymoteusz"," (Bydgoszcz)","I","38","M","","33.","(","M30-39","","9",")","","4:16 min/km","0:42:40","0:42:43","","0:42:40","","","","B","C(#d115b8)"],["207","209","39","[img:/graphics/flags/PL.svg]","Bąbiński Bartłomiej","WKB maratończyk (Włocławek)","I","39","M","","34.","(","M50-59","[img:medal2.png|height:15px]","2",")","","4:16 min/km","0:42:42","0:42:44","","0:42:42","BG(#ebebeb)","","","B","C(#d115b8)"],["73","75","40","[img:/graphics/flags/PL.svg]","Strzelecki Mariusz","parkrun Toruń (Brzozówka)","I","40","M","","35.","(","M30-39","","10",")","","4:16 min/km","0:42:49","0:42:53","","0:42:49","","","","B","C(#d115b8)"],["17","19","41","[img:/graphics/flags/PL.svg]","Słuniecki Tomasz","parkrun Toruń (Toruń)","I","41","M","","36.","(","M50-59","[img:medal3.png|height:15px]","3",")","","4:18 min/km","0:43:07","0:43:11","","0:43:07","BG(#ebebeb)","","","B","C(#d115b8)"],["7","9","42","[img:/graphics/flags/PL.svg]","Olszewski Karol","parkrun Toruń (Toruń)","I","42","M","","37.","(","M40-49","","15",")","","4:20 min/km","0:43:20","0:43:24","","0:43:20","","","","B","C(#d115b8)"],["120","122","43","[img:/graphics/flags/PL.svg]","Andrzejczak Krystian"," (Brześć Kujawski)","I","43","M","","38.","(","M30-39","","11",")","kat. Brześć K. (3M) ","4:20 min/km","0:43:26","0:43:29","","0:43:26","BG(#ebebeb)","","","B","C(#d115b8)"],["150","152","44","[img:/graphics/flags/PL.svg]","Wiśniewski Damian","Kujawsko-Pomorskie (Toruń)","I","44","M","","39.","(","M30-39","","12",")","","4:21 min/km","0:43:30","0:43:35","","0:43:30","","","","B","C(#d115b8)"],["8","10","45","[img:/graphics/flags/PL.svg]","Miedzak Karol","Parkrun Toruń (Toruń)","I","45","M","","40.","(","M30-39","","13",")","","4:22 min/km","0:43:41","0:43:43","","0:43:41","BG(#ebebeb)","","","B","C(#d115b8)"],["115","117","46","[img:/graphics/flags/PL.svg]","Gawroński Mateusz"," (Grodztwo)","I","46","M","","41.","(","M30-39","","14",")","","4:22 min/km","0:43:45","0:43:47","","0:43:45","","","","B","C(#d115b8)"],["113","115","47","[img:/graphics/flags/PL.svg]","Jeżewski Łukasz"," (Stolno)","I","47","M","","42.","(","M30-39","","15",")","","4:23 min/km","0:43:54","0:43:58","","0:43:54","BG(#ebebeb)","","","B","C(#d115b8)"],["96","98","48","[img:/graphics/flags/PL.svg]","Denis Marcin"," (Ciechocinek)","I","48","M","","43.","(","M40-49","","16",")","","4:23 min/km","0:43:58","0:44:01","","0:43:58","","","","B","C(#d115b8)"],["172","174","49","[img:/graphics/flags/PL.svg]","Szarwiński Mariusz","Parkrun Toruń (Toruń)","I","49","M","","44.","(","M30-39","","16",")","","4:24 min/km","0:44:04","0:44:05","","0:44:04","BG(#ebebeb)","","","B","C(#d115b8)"],["40","42","50","[img:/graphics/flags/PL.svg]","Bartosz Marek","GKS Fabianki (Kikół)","I","50","M","","45.","(","M40-49","","17",")","","4:25 min/km","0:44:10","0:44:17","","0:44:10","","","","B","C(#d115b8)"],["69","71","51","[img:/graphics/flags/PL.svg]","Pazderska Małgorzata","parkrun Toruń (Toruń)","I","51","K","","6.","(","K40-49","[img:medal2.png|height:15px]","2",")","","4:25 min/km","0:44:18","0:44:21","","0:44:18","BG(#ebebeb)","C(#d115b8)","C(#d115b8);B","B","C(#d115b8)"],["12","14","52","[img:/graphics/flags/PL.svg]","Miedzak Dawid","Parkrun Toruń (Toruń)","I","52","M","","46.","(","M30-39","","17",")","","4:25 min/km","0:44:19","0:44:22","","0:44:19","","","","B","C(#d115b8)"],["187","189","53","[img:/graphics/flags/PL.svg]","Łukaszewski Adrian"," (Babiak)","I","53","M","","47.","(","M40-49","","18",")","","4:26 min/km","0:44:25","0:44:27","","0:44:25","BG(#ebebeb)","","","B","C(#d115b8)"],["135","137","54","[img:/graphics/flags/PL.svg]","Wysocki Dariusz","parkrun Toruń (Toruń)","I","54","M","","48.","(","M40-49","","19",")","","4:26 min/km","0:44:25","0:44:31","","0:44:25","","","","B","C(#d115b8)"],["46","48","55","[img:/graphics/flags/PL.svg]","Ziółkowski Grzegorz","parkrun Toruń (Toruń)","I","55","M","","49.","(","M40-49","","20",")","","4:26 min/km","0:44:26","0:44:29","","0:44:26","BG(#ebebeb)","","","B","C(#d115b8)"],["32","34","56","[img:/graphics/flags/PL.svg]","Radziwonka Mariusz","Rozbiegani Lubraniec (Lubraniec)","I","56","M","","50.","(","M40-49","","21",")","kat.Lubraniec (5M)","4:27 min/km","0:44:31","0:44:34","","0:44:31","","","","B","C(#d115b8)"],["29","31","57","[img:/graphics/flags/PL.svg]","Pachucy Jakub","KUNA Team Włocławek (Włocławek)","I","57","M","","51.","(","M40-49","","22",")","","4:27 min/km","0:44:37","0:44:39","","0:44:37","BG(#ebebeb)","","","B","C(#d115b8)"],["171","173","58","[img:/graphics/flags/PL.svg]","Sławianowski Hubert"," (Lubraniec)","I","58","M","","52.","(","M20-29","","6",")","kat.Lubraniec (6M)","4:28 min/km","0:44:47","0:44:49","","0:44:47","","","","B","C(#d115b8)"],["203","205","59","[img:/graphics/flags/PL.svg]","Wojewoda Tomek","parkrun  Toruń (Totuń)","I","59","M","","53.","(","M40-49","","23",")","","4:31 min/km","0:45:12","0:45:17","","0:45:12","BG(#ebebeb)","","","B","C(#d115b8)"],["66","68","60","[img:/graphics/flags/PL.svg]","Szymański Jarosław","parkrun Toruń (Toruń)","I","60","M","","54.","(","M40-49","","24",")","","4:31 min/km","0:45:14","0:45:20","","0:45:14","","","","B","C(#d115b8)"],["196","198","61","[img:/graphics/flags/PL.svg]","Książkiewicz Jakub"," (Szpetal Górny)","I","61","M","","55.","(","M30-39","","18",")","","4:31 min/km","0:45:15","0:45:22","","0:45:15","BG(#ebebeb)","","","B","C(#d115b8)"],["124","126","62","[img:/graphics/flags/PL.svg]","Czub Paweł","Kocury (Poznań)","I","62","M","","56.","(","M30-39","","19",")","","4:32 min/km","0:45:23","0:45:34","","0:45:23","","","","B","C(#d115b8)"],["94","96","63","[img:/graphics/flags/PL.svg]","Kędzierski Mateusz"," (Choceń)","I","63","M","","57.","(","M30-39","","20",")","","4:34 min/km","0:45:42","0:45:45","","0:45:42","BG(#ebebeb)","","","B","C(#d115b8)"],["19","21","64","[img:/graphics/flags/PL.svg]","Kamiński Adrian"," (Brześć Kujawski)","I","64","M","","58.","(","M30-39","","21",")","kat. Brześć K. (4M) ","4:34 min/km","0:45:46","0:45:49","","0:45:46","","","","B","C(#d115b8)"],["38","40","65","[img:/graphics/flags/PL.svg]","Rumiński Krzysztof","WKB Maratończyk Włocławek (Włocławek)","I","65","M","","59.","(","M50-59","","4",")","","4:34 min/km","0:45:46","0:45:51","","0:45:46","BG(#ebebeb)","","","B","C(#d115b8)"],["334","360","66","[img:/graphics/flags/PL.svg]","Godlewski Krzysztof","parkrun  Toruń (Toruń)","I","66","M","","60.","(","M40-49","","25",")","","4:35 min/km","0:45:52","0:46:02","","0:45:52","","","","B","C(#d115b8)"],["134","136","67","[img:/graphics/flags/PL.svg]","Gąsiorowski Dominik","ZSCKR Stary Brześć (Bytoń)","I","67","M","","61.","(","M16-19","[img:medal2.png|height:15px]","2",")","","4:35 min/km","0:45:59","0:45:59","","0:45:59","BG(#ebebeb)","","","B","C(#d115b8)"],["80","82","68","[img:/graphics/flags/PL.svg]","Jabłoński Jarosław","GKS Fabianki (Ciechocinek)","I","68","M","","62.","(","M50-59","","5",")","","4:36 min/km","0:46:03","0:46:06","","0:46:03","","","","B","C(#d115b8)"],["153","155","69","[img:/graphics/flags/PL.svg]","Tokarski Damian","KS Zryw (Piotrków Kujawski)","I","69","M","","63.","(","M50-59","","6",")","","4:36 min/km","0:46:04","0:46:08","","0:46:04","BG(#ebebeb)","","","B","C(#d115b8)"],["47","49","70","[img:/graphics/flags/PL.svg]","Bladoszewska Monika","WKB Maratończyk Włocławek (Włocławek)","I","70","K","","7.","(","K40-49","[img:medal3.png|height:15px]","3",")","","4:37 min/km","0:46:15","0:46:18","","0:46:15","","C(#d115b8)","C(#d115b8);B","B","C(#d115b8)"],["209","211","71","[img:/graphics/flags/PL.svg]","Ruczewski Paweł"," (Włocławek)","I","71","M","","64.","(","M50-59","","7",")","","4:38 min/km","0:46:22","0:46:25","","0:46:22","BG(#ebebeb)","","","B","C(#d115b8)"],["136","138","72","[img:/graphics/flags/PL.svg]","Kozicki Roman","parkrun Toruń (Toruń)","I","72","M","","65.","(","M50-59","","8",")","","4:38 min/km","0:46:28","0:46:28","","0:46:28","","","","B","C(#d115b8)"],["27","29","73","[img:/graphics/flags/PL.svg]","Lewandowski Jakub","Urząd Miasta Włocławek (Włocławek)","I","73","M","","66.","(","M20-29","","7",")","","4:39 min/km","0:46:35","0:46:40","","0:46:35","BG(#ebebeb)","","","B","C(#d115b8)"],["45","47","74","[img:/graphics/flags/PL.svg]","Ziółkowska Natalia","Zabiegani Łubianka (Zagonowa, 7)","I","74","K","","8.","(","K30-39","[img:medal2.png|height:15px]","2",")","","4:39 min/km","0:46:38","0:46:38","","0:46:38","","C(#d115b8)","C(#d115b8);B","B","C(#d115b8)"],["156","158","75","[img:/graphics/flags/PL.svg]","Pawlaczyk Sławek","Parkrun Nowy Park Solankowy Inowrocław (Inowrocław)","I","75","M","","67.","(","M40-49","","26",")","","4:40 min/km","0:46:40","0:46:48","","0:46:40","BG(#ebebeb)","","","B","C(#d115b8)"],["70","72","76","[img:/graphics/flags/PL.svg]","Klimek Wiktor","KUNA Team Włocławek (Krukowo)","I","76","M","","68.","(","M16-19","[img:medal3.png|height:15px]","3",")","","4:42 min/km","0:47:01","0:47:03","","0:47:01","","","","B","C(#d115b8)"],["81","83","77","[img:/graphics/flags/PL.svg]","Nowak Marcin"," (Bądkowo)","I","77","M","","69.","(","M40-49","","27",")","","4:42 min/km","0:47:07","0:47:15","","0:47:07","BG(#ebebeb)","","","B","C(#d115b8)"],["33","35","78","[img:/graphics/flags/PL.svg]","Sztenderewicz Renata","KUNA Team Włocławek (Włocławek)","I","78","K","","9.","(","K40-49","","4",")","","4:43 min/km","0:47:11","0:47:12","","0:47:11","","C(#d115b8)","C(#d115b8);B","B","C(#d115b8)"],["165","167","79","[img:/graphics/flags/PL.svg]","Prątnicki Wiesław","ANWILTEAM (Włocławek)","I","79","M","","70.","(","M60-69","[img:medal1.png|height:15px]","1",")","","4:43 min/km","0:47:14","0:47:17","","0:47:14","BG(#ebebeb)","","","B","C(#d115b8)"],["61","63","80","[img:/graphics/flags/PL.svg]","Pasternak Kinga","KUNA Team Włocławek (Włocławek)","I","80","K","","10.","(","K40-49","","5",")","","4:43 min/km","0:47:15","0:47:17","","0:47:15","","C(#d115b8)","C(#d115b8);B","B","C(#d115b8)"],["159","161","81","[img:/graphics/flags/PL.svg]","Lewandowski Maciej","T.G .Sokół (Rojewo)","I","81","M","","71.","(","M30-39","","22",")","","4:44 min/km","0:47:27","0:47:32","","0:47:27","BG(#ebebeb)","","","B","C(#d115b8)"],["173","175","82","[img:/graphics/flags/PL.svg]","Baryza Radosław","Brak (Bytoń)","I","82","M","","72.","(","M30-39","","23",")","","4:45 min/km","0:47:30","0:47:43","","0:47:30","","","","B","C(#d115b8)"],["137","139","83","[img:/graphics/flags/PL.svg]","Pikulski Rafał","KS ZRYW RADZIEJÓW (Litychowo)","I","83","M","","73.","(","M40-49","","28",")","","4:45 min/km","0:47:34","0:47:43","","0:47:34","BG(#ebebeb)","","","B","C(#d115b8)"],["54","56","84","[img:/graphics/flags/PL.svg]","Czerenkiewicz-Pałucka Joanna","KUNA Team Włocławek (Machnacz)","I","84","K","","11.","(","K50-59","[img:medal1.png|height:15px]","1",")","kat. Brześć K. (1K) ","4:46 min/km","0:47:42","0:47:44","","0:47:42","","C(#d115b8)","C(#d115b8);B","B","C(#d115b8)"],["166","168","85","[img:/graphics/flags/PL.svg]","Skibiński Łukasz"," (Chełmica Cukrownia)","I","85","M","","74.","(","M40-49","","29",")","","4:47 min/km","0:47:58","0:48:09","","0:47:58","BG(#ebebeb)","","","B","C(#d115b8)"],["132","134","86","[img:/graphics/flags/PL.svg]","Mączka Zbigniew","Parkrun Toruń (Toruń)","I","86","M","","75.","(","M60-69","[img:medal2.png|height:15px]","2",")","","4:47 min/km","0:47:58","0:48:02","","0:47:58","","","","B","C(#d115b8)"],["199","201","87","[img:/graphics/flags/PL.svg]","Danielewicz Daria","T.G. Sokół Gniewkowo (Gniewkowo)","I","87","K","","12.","(","K20-29","[img:medal1.png|height:15px]","1",")","","4:48 min/km","0:48:03","0:48:08","","0:48:03","BG(#ebebeb)","C(#d115b8)","C(#d115b8);B","B","C(#d115b8)"],["174","176","88","[img:/graphics/flags/PL.svg]","Pawłowski Tomasz","4Rblog Powidz (Gniezno)","I","88","M","","76.","(","M30-39","","24",")","","4:49 min/km","0:48:12","0:48:20","","0:48:12","","","","B","C(#d115b8)"],["193","195","89","[img:/graphics/flags/PL.svg]","Gwóźdź Aneta","Biegaj z Dymkiem (Płock)","I","89","K","","13.","(","K40-49","","6",")","","4:49 min/km","0:48:14","0:48:17","","0:48:14","BG(#ebebeb)","C(#d115b8)","C(#d115b8);B","B","C(#d115b8)"],["142","144","90","[img:/graphics/flags/PL.svg]","Jarzecki Sławomir","Kuna Team (Marianki)","I","90","M","","77.","(","M50-59","","9",")","kat. Brześć K. (5M) ","4:49 min/km","0:48:14","0:48:16","","0:48:14","","","","B","C(#d115b8)"],["41","43","91","[img:/graphics/flags/PL.svg]","Bartosz Mariola","GKS Fabianki (Kikół)","I","91","K","","14.","(","K40-49","","7",")","","4:50 min/km","0:48:23","0:48:34","","0:48:23","BG(#ebebeb)","C(#d115b8)","C(#d115b8);B","B","C(#d115b8)"],["13","15","92","[img:/graphics/flags/PL.svg]","Pankowska-Siwiak Agata","SamiSwoi (Inowrocław)","I","92","K","","15.","(","K30-39","[img:medal3.png|height:15px]","3",")","","4:50 min/km","0:48:24","0:48:30","","0:48:24","","C(#d115b8)","C(#d115b8);B","B","C(#d115b8)"],["114","116","93","[img:/graphics/flags/PL.svg]","Jeżewska Edyta"," (Stolno)","I","93","K","","16.","(","K30-39","","4",")","","4:50 min/km","0:48:25","0:48:28","","0:48:25","BG(#ebebeb)","C(#d115b8)","C(#d115b8);B","B","C(#d115b8)"],["154","156","94","[img:/graphics/flags/PL.svg]","Tokarska Aneta","KS ZRYW Radziejów (Piotrków Kujawski)","I","94","K","","17.","(","K50-59","[img:medal2.png|height:15px]","2",")","","4:51 min/km","0:48:36","0:48:42","","0:48:36","","C(#d115b8)","C(#d115b8);B","B","C(#d115b8)"],["92","94","95","[img:/graphics/flags/PL.svg]","Olesiński Krzysztof","WKB Maratończyk Włocławek (Włocławek)","I","95","M","","78.","(","M40-49","","30",")","","4:51 min/km","0:48:39","0:48:39","","0:48:39","BG(#ebebeb)","","","B","C(#d115b8)"],["109","111","96","[img:/graphics/flags/PL.svg]","Berebecki Roman","RKS LECH RYPIN (Rypin)","I","96","M","","79.","(","M70+","[img:medal1.png|height:15px]","1",")","","4:52 min/km","0:48:40","0:48:40","","0:48:40","","","","B","C(#d115b8)"],["91","93","97","[img:/graphics/flags/PL.svg]","Kunecka Anita","KUNA Team Włocławek (WŁocŁawek)","I","97","K","","18.","(","K40-49","","8",")","","4:52 min/km","0:48:41","0:48:42","","0:48:41","BG(#ebebeb)","C(#d115b8)","C(#d115b8);B","B","C(#d115b8)"],["140","142","98","[img:/graphics/flags/PL.svg]","Fedde Maksymilian","parkrun Nowy Park Solankowy, Inowrocław (Inowrocław)","I","98","M","","80.","(","M40-49","","31",")","","4:53 min/km","0:48:51","0:48:58","","0:48:51","","","","B","C(#d115b8)"],["25","27","99","[img:/graphics/flags/PL.svg]","Klimek Magdalena","KUNA Team Włocławek (Włocławek)","I","99","K","","19.","(","K40-49","","9",")","","4:54 min/km","0:49:02","0:49:08","","0:49:02","BG(#ebebeb)","C(#d115b8)","C(#d115b8);B","B","C(#d115b8)"],["164","166","100","[img:/graphics/flags/PL.svg]","Hussein Anna","parkun Toruń (Konradowo)","I","100","K","","20.","(","K40-49","","10",")","","4:55 min/km","0:49:10","0:49:16","","0:49:10","","C(#d115b8)","C(#d115b8);B","B","C(#d115b8)"],["129","131","101","[img:/graphics/flags/PL.svg]","Jaworski Jarosław","Parkrun Toruń (Toruń)","I","101","M","","81.","(","M50-59","","10",")","","4:55 min/km","0:49:15","0:49:20","","0:49:15","BG(#ebebeb)","","","B","C(#d115b8)"],["90","92","102","[img:/graphics/flags/PL.svg]","Jasiński Sylwester","WKB Maratończyk Włocławek (Ośmiałowo)","I","102","M","","82.","(","M30-39","","25",")","","4:57 min/km","0:49:32","0:49:42","","0:49:32","","","","B","C(#d115b8)"],["191","193","103","[img:/graphics/flags/PL.svg]","Brzustowicz Marek"," (Cisew)","I","103","M","","83.","(","M70+","[img:medal2.png|height:15px]","2",")","","4:58 min/km","0:49:49","0:49:53","","0:49:49","BG(#ebebeb)","","","B","C(#d115b8)"],["64","66","104","[img:/graphics/flags/PL.svg]","Glonek Karolina"," (Boniewo)","I","104","K","","21.","(","K40-49","","11",")","","4:59 min/km","0:49:57","0:50:01","","0:49:57","","C(#d115b8)","C(#d115b8);B","B","C(#d115b8)"],["198","200","105","[img:/graphics/flags/PL.svg]","Stawarska Elżbieta","parkrun Toruń (Toruń)","I","105","K","","22.","(","K40-49","","12",")","","5:00 min/km","0:50:08","0:50:15","","0:50:08","BG(#ebebeb)","C(#d115b8)","C(#d115b8);B","B","C(#d115b8)"],["138","140","106","[img:/graphics/flags/PL.svg]","Pikulska Joanna","KS ZRYW RADZIEJÓW (Litychowo)","I","106","K","","23.","(","K30-39","","5",")","","5:02 min/km","0:50:24","0:50:33","","0:50:24","","C(#d115b8)","C(#d115b8);B","B","C(#d115b8)"],["21","23","107","[img:/graphics/flags/PL.svg]","Czerniak Justyna","ROZBIEGANI LUBRANIEC (Lubraniec)","I","107","K","","24.","(","K30-39","","6",")","kat.Lubraniec (1K)","5:03 min/km","0:50:38","0:50:38","","0:50:38","BG(#ebebeb)","C(#d115b8)","C(#d115b8);B","B","C(#d115b8)"],["1","3","108","[img:/graphics/flags/PL.svg]","Gac Monika","T.G.Sokół Gniewkowo (Gniewkowo)","I","108","K","","25.","(","K50-59","[img:medal3.png|height:15px]","3",")","","5:03 min/km","0:50:38","0:50:45","","0:50:38","","C(#d115b8)","C(#d115b8);B","B","C(#d115b8)"],["108","110","109","[img:/graphics/flags/PL.svg]","Olszewski Adam","RKS LECH RYPIN (Rypin)","I","109","M","","84.","(","M60-69","[img:medal3.png|height:15px]","3",")","","5:04 min/km","0:50:43","0:50:50","","0:50:43","BG(#ebebeb)","","","B","C(#d115b8)"],["181","183","110","[img:/graphics/flags/PL.svg]","Muraszewska Kinga","KUNA Team Włocławek (Włocławek)","I","110","K","","26.","(","K40-49","","13",")","","5:04 min/km","0:50:45","0:50:48","","0:50:45","","C(#d115b8)","C(#d115b8);B","B","C(#d115b8)"],["52","54","111","[img:/graphics/flags/PL.svg]","Bińczarska Monika","WKB MARATOŃCZYK WŁOCŁAWEK (WŁocŁawek)","I","111","K","","27.","(","K40-49","","14",")","","5:04 min/km","0:50:47","0:50:49","","0:50:47","BG(#ebebeb)","C(#d115b8)","C(#d115b8);B","B","C(#d115b8)"],["84","86","112","[img:/graphics/flags/PL.svg]","Lewandowski Krzysztof"," (Brześć Kujawski)","I","112","M","","85.","(","M50-59","","11",")","kat. Brześć K. (6M) ","5:05 min/km","0:50:52","0:50:57","","0:50:52","","","","B","C(#d115b8)"],["161","163","113","[img:/graphics/flags/PL.svg]","Kryszak Klaudia","T.G. Sokół Gniewkowo (Inowrocław)","I","113","K","","28.","(","K30-39","","7",")","","5:05 min/km","0:50:53","0:51:00","","0:50:53","BG(#ebebeb)","C(#d115b8)","C(#d115b8);B","B","C(#d115b8)"],["121","123","114","[img:/graphics/flags/PL.svg]","Chamryga Marcin"," (Brześć Kujawski)","I","114","M","","86.","(","M20-29","","8",")","kat. Brześć K. (7M) ","5:07 min/km","0:51:17","0:51:24","","0:51:17","","","","B","C(#d115b8)"],["117","119","115","[img:/graphics/flags/PL.svg]","Lewandowski Tymon"," (Brześć Kujawski)","I","115","M","","87.","(","M20-29","","9",")","kat. Brześć K. (8M) ","5:07 min/km","0:51:18","0:51:22","","0:51:18","BG(#ebebeb)","","","B","C(#d115b8)"],["5","7","116","[img:/graphics/flags/PL.svg]","Słuniecka Aleksandra","parkrun Toruń (Toruń)","I","116","K","","29.","(","K20-29","[img:medal2.png|height:15px]","2",")","","5:08 min/km","0:51:20","0:51:26","","0:51:20","","C(#d115b8)","C(#d115b8);B","B","C(#d115b8)"],["201","203","117","[img:/graphics/flags/PL.svg]","Bruzda Paweł"," (Brześć Kujawski)","I","117","M","","88.","(","M40-49","","32",")","kat. Brześć K. (9M) ","5:11 min/km","0:51:55","0:52:02","","0:51:55","BG(#ebebeb)","","","B","C(#d115b8)"],["23","25","118","[img:/graphics/flags/PL.svg]","Gajewski Maciej","Urząd Miasta Włocławek (Włocławek)","I","118","M","","89.","(","M40-49","","33",")","","5:12 min/km","0:52:00","0:52:05","","0:52:00","","","","B","C(#d115b8)"],["30","32","119","[img:/graphics/flags/PL.svg]","Pasternak Marcin","KUNA Team Włocławek (Włocławek)","I","119","M","","90.","(","M40-49","","34",")","","5:12 min/km","0:52:01","0:52:05","","0:52:01","BG(#ebebeb)","","","B","C(#d115b8)"],["4","6","120","[img:/graphics/flags/PL.svg]","Sadokierski Dawid"," (Brześć Kujawski)","I","120","M","","91.","(","M30-39","","26",")","kat. Brześć K. (10M) ","5:12 min/km","0:52:09","0:52:11","","0:52:09","","","","B","C(#d115b8)"],["169","171","121","[img:/graphics/flags/PL.svg]","Wiśniewski Karol"," (Toruń)","I","121","M","","92.","(","M20-29","","10",")","","5:14 min/km","0:52:22","0:52:30","","0:52:22","BG(#ebebeb)","","","B","C(#d115b8)"],["95","97","122","[img:/graphics/flags/PL.svg]","Ziółkowski Mieczysław","TG Sokół Gniewowo (Janikowo)","I","122","M","","93.","(","M60-69","","4",")","","5:15 min/km","0:52:32","0:52:38","","0:52:32","","","","B","C(#d115b8)"],["93","95","123","[img:/graphics/flags/PL.svg]","Pyszkowski Piotr","WKB Maratończyk Włocławek (Krzewent)","I","123","M","","94.","(","M30-39","","27",")","","5:15 min/km","0:52:35","0:52:40","","0:52:35","BG(#ebebeb)","","","B","C(#d115b8)"],["86","88","124","[img:/graphics/flags/PL.svg]","Janiszewski Darek","Parkrun Toruń (Toruń)","I","124","M","","95.","(","M50-59","","12",")","","5:16 min/km","0:52:44","0:52:50","","0:52:44","","","","B","C(#d115b8)"],["98","100","125","[img:/graphics/flags/PL.svg]","Kwiatkowski Kacper"," (Brześć Kujawski)","I","125","M","","96.","(","M20-29","","11",")","kat. Brześć K. (11M) ","5:16 min/km","0:52:47","0:53:00","","0:52:47","BG(#ebebeb)","","","B","C(#d115b8)"],["130","132","126","[img:/graphics/flags/PL.svg]","Roszak Zbigniew","Wataha łączy nas bieganie (Gniewkowo)","I","126","M","","97.","(","M30-39","","28",")","","5:17 min/km","0:52:55","0:53:01","","0:52:55","","","","B","C(#d115b8)"],["139","141","127","[img:/graphics/flags/PL.svg]","Biernat Magdalena","TG SOKÓŁ Gniewkowo (Inowrocław)","I","127","K","","30.","(","K40-49","","15",")","","5:17 min/km","0:52:57","0:53:05","","0:52:57","BG(#ebebeb)","C(#d115b8)","C(#d115b8);B","B","C(#d115b8)"],["105","107","128","[img:/graphics/flags/PL.svg]","Wróblewski Krzysztof","WKB Maratończyk Włocławek (Włocławek)","I","128","M","","98.","(","M40-49","","35",")","","5:17 min/km","0:52:59","0:53:04","","0:52:59","","","","B","C(#d115b8)"],["110","112","129","[img:/graphics/flags/PL.svg]","Marciniak Witold","WKB Maratończyk Włocławek (Włocławek)","I","129","M","","99.","(","M40-49","","36",")","","5:19 min/km","0:53:11","0:53:21","","0:53:11","BG(#ebebeb)","","","B","C(#d115b8)"],["62","64","130","[img:/graphics/flags/PL.svg]","Wasielewska Kinga"," (Włocławek)","I","130","K","","31.","(","K20-29","[img:medal3.png|height:15px]","3",")","","5:19 min/km","0:53:13","0:53:13","","0:53:13","","C(#d115b8)","C(#d115b8);B","B","C(#d115b8)"],["102","104","131","[img:/graphics/flags/PL.svg]","Lewandowski Władysław","T.G SOKÓŁ GNIEWKOWO (Janikowo)","I","131","M","","100.","(","M70+","[img:medal3.png|height:15px]","3",")","","5:21 min/km","0:53:39","0:53:47","","0:53:39","BG(#ebebeb)","","","B","C(#d115b8)"],["78","80","132","[img:/graphics/flags/PL.svg]","Frąckowiak Paweł"," (Janikowo)","I","132","M","","101.","(","M16-19","","4",")","","5:22 min/km","0:53:40","0:53:49","","0:53:40","","","","B","C(#d115b8)"],["131","133","133","[img:/graphics/flags/PL.svg]","Żyłkowska Krystyna","parkrun Toruń (Torun)","I","133","K","","32.","(","K60-69","[img:medal1.png|height:15px]","1",")","","5:22 min/km","0:53:48","0:53:51","","0:53:48","BG(#ebebeb)","C(#d115b8)","C(#d115b8);B","B","C(#d115b8)"],["332","358","134","[img:/graphics/flags/PL.svg]","Ciski Zbigniew"," (Toru)","I","134","M","","102.","(","M60-69","","5",")","","5:23 min/km","0:53:53","0:53:58","","0:53:53","","","","B","C(#d115b8)"],["119","121","135","[img:/graphics/flags/PL.svg]","Ciski Przemysław","Kujawsko-Pomorskie (ToruŃ)","I","135","M","","103.","(","M40-49","","37",")","","5:23 min/km","0:53:53","0:53:59","","0:53:53","BG(#ebebeb)","","","B","C(#d115b8)"],["14","16","136","[img:/graphics/flags/PL.svg]","Piotrowicz Ireneusz"," (Piotrków Kujawski)","I","136","M","","104.","(","M60-69","","6",")","","5:23 min/km","0:53:58","0:54:08","","0:53:58","","","","B","C(#d115b8)"],["76","78","137","[img:/graphics/flags/PL.svg]","Koperski Sebastian","parkrun Toruń (Czernikowo)","I","137","M","","105.","(","M40-49","","38",")","","5:25 min/km","0:54:12","0:54:22","","0:54:12","BG(#ebebeb)","","","B","C(#d115b8)"],["11","13","138","[img:/graphics/flags/PL.svg]","Janeczko Katarzyna","Parkrun Toruń (Toruń)","I","138","K","","33.","(","K40-49","","16",")","","5:25 min/km","0:54:12","0:54:23","","0:54:12","","C(#d115b8)","C(#d115b8);B","B","C(#d115b8)"],["186","188","139","[img:/graphics/flags/PL.svg]","Kaczmarek Katarzyna","- (Chełmce)","I","139","K","","34.","(","K50-59","","4",")","","5:25 min/km","0:54:15","0:54:25","","0:54:15","BG(#ebebeb)","C(#d115b8)","C(#d115b8);B","B","C(#d115b8)"],["20","22","140","[img:/graphics/flags/PL.svg]","Czajkowska Aleksandra"," (Bydgoszcz)","I","140","K","","35.","(","K20-29","","4",")","","5:28 min/km","0:54:41","0:54:52","","0:54:41","","C(#d115b8)","C(#d115b8);B","B","C(#d115b8)"],["126","128","141","[img:/graphics/flags/PL.svg]","Kamiński Łukasz"," (Toruń)","I","141","M","","106.","(","M40-49","","39",")","","5:30 min/km","0:55:03","0:55:11","","0:55:03","BG(#ebebeb)","","","B","C(#d115b8)"],["24","26","142","[img:/graphics/flags/PL.svg]","Jagodzińska Małgorzata","Rozbiegani Lubraniec (Lubraniec)","I","142","K","","36.","(","K40-49","","17",")","kat.Lubraniec (2K)","5:30 min/km","0:55:06","0:55:10","","0:55:06","","C(#d115b8)","C(#d115b8);B","B","C(#d115b8)"],["182","184","143","[img:/graphics/flags/PL.svg]","Piasecki Arkadiusz","Urząd Miasta Włocławek (Włocławek)","I","143","M","","107.","(","M50-59","","13",")","","5:33 min/km","0:55:37","0:55:38","","0:55:37","BG(#ebebeb)","","","B","C(#d115b8)"],["168","170","144","[img:/graphics/flags/PL.svg]","Majcher Sławomira"," (Włocławek)","I","144","K","","37.","(","K40-49","","18",")","","5:33 min/km","0:55:38","0:55:38","","0:55:38","","C(#d115b8)","C(#d115b8);B","B","C(#d115b8)"],["82","84","145","[img:/graphics/flags/PL.svg]","Franczyk Krzysztof"," (Lubraniec)","I","145","M","","108.","(","M40-49","","40",")","kat.Lubraniec (7M)","5:35 min/km","0:55:55","0:56:02","","0:55:55","BG(#ebebeb)","","","B","C(#d115b8)"],["50","52","146","[img:/graphics/flags/PL.svg]","Gabizdalska Alicja","T.G. Sokół Gniewkowo (Gniewkowo)","I","146","K","","38.","(","K20-29","","5",")","","5:36 min/km","0:56:08","0:56:17","","0:56:08","","C(#d115b8)","C(#d115b8);B","B","C(#d115b8)"],["49","51","147","[img:/graphics/flags/PL.svg]","Torgowski Krzysztof","T.G. Sokół Gniewkowo (Gniewkowo)","I","147","M","","109.","(","M30-39","","29",")","","5:36 min/km","0:56:09","0:56:18","","0:56:09","BG(#ebebeb)","","","B","C(#d115b8)"],["72","74","148","[img:/graphics/flags/PL.svg]","Iglewski Andrzej","Rozbiegani Lubraniec (Lubraniec)","I","148","M","","110.","(","M60-69","","7",")","kat.Lubraniec (8M)","5:37 min/km","0:56:12","0:56:22","","0:56:12","","","","B","C(#d115b8)"],["31","33","149","[img:/graphics/flags/PL.svg]","Pawłowska Anna","Rozbiegani Lubraniec (Lubraniec)","I","149","K","","39.","(","K30-39","","8",")","kat.Lubraniec (3K)","5:37 min/km","0:56:12","0:56:22","","0:56:12","BG(#ebebeb)","C(#d115b8)","C(#d115b8);B","B","C(#d115b8)"],["116","118","150","[img:/graphics/flags/PL.svg]","Lewandowska Nadia"," (Brześć Kujawski)","I","150","K","","40.","(","K20-29","","6",")","kat. Brześć K. (2K) ","5:37 min/km","0:56:13","0:56:21","","0:56:13","","C(#d115b8)","C(#d115b8);B","B","C(#d115b8)"],["208","210","151","[img:/graphics/flags/PL.svg]","Marczewski Rafał"," (Kruszyn)","I","151","M","","111.","(","M40-49","","41",")","","5:39 min/km","0:56:37","0:56:50","","0:56:37","BG(#ebebeb)","","","B","C(#d115b8)"],["75","77","152","[img:/graphics/flags/PL.svg]","Wojciechowski Sławomir","parkrun Toruń (Lubicz Dolny)","I","152","M","","112.","(","M40-49","","42",")","","5:40 min/km","0:56:48","0:56:57","","0:56:48","","","","B","C(#d115b8)"],["10","12","153","[img:/graphics/flags/PL.svg]","Drawert Ewa"," (Łubki)","I","153","K","","41.","(","K40-49","","19",")","","5:41 min/km","0:56:50","0:56:54","","0:56:50","BG(#ebebeb)","C(#d115b8)","C(#d115b8);B","B","C(#d115b8)"],["125","127","154","[img:/graphics/flags/PL.svg]","Antecki Marcin"," (Brześć Kujawski)","I","154","M","","113.","(","M40-49","","43",")","kat. Brześć K. (12M) ","5:42 min/km","0:57:05","0:57:16","","0:57:05","","","","B","C(#d115b8)"],["85","87","155","[img:/graphics/flags/PL.svg]","Lewandowska Beata"," (Brześć Kujawski)","I","155","K","","42.","(","K40-49","","20",")","kat. Brześć K. (3K) ","5:42 min/km","0:57:09","0:57:16","","0:57:09","BG(#ebebeb)","C(#d115b8)","C(#d115b8);B","B","C(#d115b8)"],["157","159","156","[img:/graphics/flags/PL.svg]","Sekretarski Błażej"," (Brześć Kujawski)","I","156","M","","114.","(","M30-39","","30",")","kat. Brześć K. (13M) ","5:43 min/km","0:57:11","0:57:18","","0:57:11","","","","B","C(#d115b8)"],["58","60","157","[img:/graphics/flags/PL.svg]","Rybowska Magdalena","Drużyna Rozbiegani Lubraniec (Lubraniec)","I","157","K","","43.","(","K50-59","","5",")","kat.Lubraniec (4K)","5:43 min/km","0:57:19","0:57:29","","0:57:19","BG(#ebebeb)","C(#d115b8)","C(#d115b8);B","B","C(#d115b8)"],["104","106","158","[img:/graphics/flags/PL.svg]","Przybysz Kacper"," (Lubraniec)","I","158","M","","115.","(","M20-29","","12",")","kat.Lubraniec (9M)","5:45 min/km","0:57:39","0:57:51","","0:57:39","","","","B","C(#d115b8)"],["65","67","159","[img:/graphics/flags/PL.svg]","Łapczyński Stefan","Niezrzeszony (Konstantynów Łódzki)","I","159","M","","116.","(","M70+","","4",")","","5:46 min/km","0:57:45","0:57:53","","0:57:45","BG(#ebebeb)","","","B","C(#d115b8)"],["59","61","160","[img:/graphics/flags/PL.svg]","Zufla Ewelina","Rozbiegani Lubraniec (Lubraniec)","I","160","K","","44.","(","K40-49","","21",")","kat.Lubraniec (5K)","5:48 min/km","0:58:04","0:58:14","","0:58:04","","C(#d115b8)","C(#d115b8);B","B","C(#d115b8)"],["6","8","161","[img:/graphics/flags/PL.svg]","Stawicki Łukasz"," (Toruń)","I","161","M","","117.","(","M40-49","","44",")","","5:48 min/km","0:58:05","0:58:08","","0:58:05","BG(#ebebeb)","","","B","C(#d115b8)"],["34","36","162","[img:/graphics/flags/PL.svg]","Ziółkowska Justyna","Rozbiegani Lubraniec (Lubraniec)","I","162","K","","45.","(","K40-49","","22",")","kat.Lubraniec (6K)","5:48 min/km","0:58:06","0:58:15","","0:58:06","","C(#d115b8)","C(#d115b8);B","B","C(#d115b8)"],["197","199","163","[img:/graphics/flags/PL.svg]","Grzeszak Weronika"," (Nowy Dwór Mazowiecki)","I","163","K","","46.","(","K30-39","","9",")","","5:50 min/km","0:58:22","0:58:31","","0:58:22","BG(#ebebeb)","C(#d115b8)","C(#d115b8);B","B","C(#d115b8)"],["100","102","164","[img:/graphics/flags/PL.svg]","Czerwinski Rafał","K.S. Zagłębie Piechcin (Torun)","I","164","M","","118.","(","M30-39","","31",")","","5:51 min/km","0:58:33","0:58:39","","0:58:33","","","","B","C(#d115b8)"],["122","124","165","[img:/graphics/flags/PL.svg]","Masłowska Agnieszka"," (Włocławek)","I","165","K","","47.","(","K50-59","","6",")","","5:52 min/km","0:58:44","0:58:53","","0:58:44","BG(#ebebeb)","C(#d115b8)","C(#d115b8);B","B","C(#d115b8)"],["160","162","166","[img:/graphics/flags/PL.svg]","Tkaczuk Jolanta","T.G. Sokół (Gniewkowo)","I","166","K","","48.","(","K60-69","[img:medal2.png|height:15px]","2",")","","5:52 min/km","0:58:48","0:58:56","","0:58:48","","C(#d115b8)","C(#d115b8);B","B","C(#d115b8)"],["188","190","167","[img:/graphics/flags/PL.svg]","Ziomkowska Angelika"," (Brześć Kujawski)","I","167","K","","49.","(","K20-29","","7",")","kat. Brześć K. (4K) ","5:53 min/km","0:58:53","0:59:04","","0:58:53","BG(#ebebeb)","C(#d115b8)","C(#d115b8);B","B","C(#d115b8)"],["183","185","168","[img:/graphics/flags/PL.svg]","Gałka Agnieszka"," (Krotoszyn)","I","168","K","","50.","(","K20-29","","8",")","","5:56 min/km","0:59:25","0:59:35","","0:59:25","","C(#d115b8)","C(#d115b8);B","B","C(#d115b8)"],["190","192","169","[img:/graphics/flags/PL.svg]","Humańska Alicja","Rozbiegani Lubraniec (Lubraniec)","I","169","K","","51.","(","K16-19","[img:medal1.png|height:15px]","1",")","kat.Lubraniec (7K)","5:58 min/km","0:59:45","0:59:54","","0:59:45","BG(#ebebeb)","C(#d115b8)","C(#d115b8);B","B","C(#d115b8)"],["184","186","170","[img:/graphics/flags/PL.svg]","Moderska Edyta"," (Skępe)","I","170","K","","52.","(","K40-49","","23",")","","5:58 min/km","0:59:48","0:59:58","","0:59:48","","C(#d115b8)","C(#d115b8);B","B","C(#d115b8)"],["158","160","171","[img:/graphics/flags/PL.svg]","Graczykowska Ania","Biegamy Lekką Nóżką (Inowrocław)","I","171","K","","53.","(","K40-49","","24",")","","6:00 min/km","1:00:00","1:00:10","","1:00:00","BG(#ebebeb)","C(#d115b8)","C(#d115b8);B","B","C(#d115b8)"],["63","65","172","[img:/graphics/flags/PL.svg]","Piontek Elżbieta"," (Bydgoszcz)","I","172","K","","54.","(","K60-69","[img:medal3.png|height:15px]","3",")","","6:11 min/km","1:01:55","1:02:04","","1:01:55","","C(#d115b8)","C(#d115b8);B","B","C(#d115b8)"],["42","44","173","[img:/graphics/flags/PL.svg]","Śląski Krzysztof","Plewiska (Plewiska)","I","173","M","","119.","(","M40-49","","45",")","","6:13 min/km","1:02:12","1:02:23","","1:02:12","BG(#ebebeb)","","","B","C(#d115b8)"],["205","207","174","[img:/graphics/flags/PL.svg]","Smoleń Agnieszka","parkrun Toruń (Toruń)","I","174","K","","55.","(","K40-49","","25",")","","6:18 min/km","1:03:02","1:03:13","","1:03:02","","C(#d115b8)","C(#d115b8);B","B","C(#d115b8)"],["152","154","175","[img:/graphics/flags/PL.svg]","Sowiński Edmund","TKKF Płock (Płock)","I","175","M","","120.","(","M70+","","5",")","","6:20 min/km","1:03:26","1:03:33","","1:03:26","BG(#ebebeb)","","","B","C(#d115b8)"],["22","24","176","[img:/graphics/flags/PL.svg]","Dłoniak Edmund","SOKÓŁ GNIEWKOWO (Gniewkowo)","I","176","M","","121.","(","M70+","","6",")","","6:23 min/km","1:03:52","1:04:00","","1:03:52","","","","B","C(#d115b8)"],["37","39","177","[img:/graphics/flags/PL.svg]","Roszak Sylwester","Lubraniec (Brześć Kujawski)","I","177","M","","122.","(","M40-49","","46",")","kat. Brześć K. (14M) ","6:41 min/km","1:06:56","1:07:09","","1:06:56","BG(#ebebeb)","","","B","C(#d115b8)"],["195","197","178","[img:/graphics/flags/PL.svg]","Grzeszak Danuta"," (Mogilno)","I","178","K","","56.","(","K70+","[img:medal1.png|height:15px]","1",")","","6:42 min/km","1:07:02","1:07:11","","1:07:02","","C(#d115b8)","C(#d115b8);B","B","C(#d115b8)"],["101","103","179","[img:/graphics/flags/PL.svg]","Bladoszewski Michał"," (Włocławek)","I","179","M","","123.","(","M20-29","","13",")","kat.Lubraniec (10M)","6:47 min/km","1:07:58","1:08:11","","1:07:58","BG(#ebebeb)","","","B","C(#d115b8)"],["9","11","180","[img:/graphics/flags/PL.svg]","Andrzejczak Weronika"," (Brześć Kujawski)","I","180","K","","57.","(","K20-29","","9",")","kat. Brześć K. (5K) ","6:51 min/km","1:08:34","1:08:42","","1:08:34","","C(#d115b8)","C(#d115b8);B","B","C(#d115b8)"],["67","69","181","[img:/graphics/flags/PL.svg]","Sorbian Weronika"," (Poznań)","I","181","K","","58.","(","K20-29","","10",")","","6:51 min/km","1:08:34","1:08:43","","1:08:34","BG(#ebebeb)","C(#d115b8)","C(#d115b8);B","B","C(#d115b8)"],["179","181","182","[img:/graphics/flags/PL.svg]","Czajkowska Lidia"," (Baruchowo)","I","182","K","","59.","(","K20-29","","11",")","","6:59 min/km","1:09:50","1:10:01","","1:09:50","","C(#d115b8)","C(#d115b8);B","B","C(#d115b8)"],["206","208","183","[img:/graphics/flags/PL.svg]","Bugdał Justyna"," (Gostynin)","I","183","K","","60.","(","K20-29","","12",")","","6:59 min/km","1:09:51","1:10:01","","1:09:51","BG(#ebebeb)","C(#d115b8)","C(#d115b8);B","B","C(#d115b8)"],["127","129","184","[img:/graphics/flags/PL.svg]","Raczkowski Alan"," (Luboń)","I","184","M","","124.","(","M30-39","","32",")","","7:00 min/km","1:10:04","1:10:15","","1:10:04","","","","B","C(#d115b8)"],["170","172","185","[img:/graphics/flags/PL.svg]","Lewandowski Wojciech"," (Lipno)","I","185","M","","125.","(","M70+","","7",")","","7:04 min/km","1:10:40","1:10:49","","1:10:40","BG(#ebebeb)","","","B","C(#d115b8)"],["74","76","186","[img:/graphics/flags/PL.svg]","Dziełak Patrycja"," (Czystochleb)","I","186","K","","61.","(","K16-19","[img:medal2.png|height:15px]","2",")","","7:14 min/km","1:12:20","1:12:30","","1:12:20","","C(#d115b8)","C(#d115b8);B","B","C(#d115b8)"],["106","108","187","[img:/graphics/flags/PL.svg]","Boniecka Teresa","RKS LECH RYPIN (Radomin)","I","187","K","","62.","(","K50-59","","7",")","","7:20 min/km","1:13:29","1:13:33","","1:13:29","BG(#ebebeb)","C(#d115b8)","C(#d115b8);B","B","C(#d115b8)"],["189","191","188","[img:/graphics/flags/PL.svg]","Dolatowska Kinga"," (Lubraniec)","I","188","K","","63.","(","K20-29","","13",")","kat.Lubraniec (8K)","7:21 min/km","1:13:36","1:13:46","","1:13:36","","C(#d115b8)","C(#d115b8);B","B","C(#d115b8)"],["16","18","189","[img:/graphics/flags/PL.svg]","Koprowski Zbyszek","WKB  MARATONCZYK (Włocławek)","I","189","M","","126.","(","M50-59","","14",")","","7:24 min/km","1:14:06","1:14:11","","1:14:06","BG(#ebebeb)","","","B","C(#d115b8)"],["180","182","190","[img:/graphics/flags/PL.svg]","Blaszczak Stanislaw","Wkb Maratonczyk Wloclawek (Skepe)","I","190","M","","127.","(","M70+","","8",")","","7:32 min/km","1:15:25","1:15:38","","1:15:25","","","","B","C(#d115b8)"],["107","109","191","[img:/graphics/flags/PL.svg]","Gerka Krzysztof","RKS LECH RYPIN (Rypin)","I","191","M","","128.","(","M60-69","","8",")","","8:26 min/km","1:24:20","1:24:32","","1:24:20","BG(#ebebeb)","","","B","C(#d115b8)"],["133","135","192","[img:/graphics/flags/PL.svg]","Chamryga Adrianna"," (Brześć Kujawski)","I","192","K","","64.","(","K30-39","","10",")","kat. Brześć K. (6K) ","8:30 min/km","1:25:06","1:25:16","","1:25:06","","C(#d115b8)","C(#d115b8);B","B","C(#d115b8)"],["103","105","193","[img:/graphics/flags/PL.svg]","Chamryga Slawomir"," (Brześć Kujawski)","I","193","M","","129.","(","M50-59","","15",")","kat. Brześć K. (15M) ","8:30 min/km","1:25:09","1:25:17","","1:25:09","BG(#ebebeb)","","","B","C(#d115b8)"],["48","50","194","[img:/graphics/flags/PL.svg]","Sobczak Tomasz"," (Poznań)","I","194","M","","130.","(","M50-59","","16",")","","19:39 min/km","3:16:35","3:16:35","","3:16:35","","","","B","C(#d115b8)"],["15","17","195","[img:/graphics/flags/PL.svg]","Tomtas Konrad"," (Inowrocław)","I","195","M","","131.","(","M50-59","","17",")","","19:39 min/km","3:16:35","3:16:35","","3:16:35","BG(#ebebeb)","","","B","C(#d115b8)"],["148","150","196","[img:/graphics/flags/PL.svg]","Piekut Stefan","TKKF Płock (Płock)","I","196","M","","132.","(","M70+","","9",")","","19:39 min/km","3:16:35","3:16:35","","3:16:35","","","","B","C(#d115b8)"],["149","151","197","[img:/graphics/flags/PL.svg]","Wierski Jarosław","Kujawsko-Pomorskie (Mała Nieszawka)","I","197","M","","133.","(","M50-59","","18",")","","19:39 min/km","3:16:35","3:16:35","","3:16:35","BG(#ebebeb)","","","B","C(#d115b8)"],["185","187","198","[img:/graphics/flags/PL.svg]","Kołucki Stefan","SFORA BMK (Warszawa)","I","198","M","","134.","(","M30-39","","33",")","","19:39 min/km","3:16:35","3:16:35","","3:16:35","","","","B","C(#d115b8)"],["202","204","199","[img:/graphics/flags/PL.svg]","Sadowski Łukasz"," (Słupno)","I","199","M","","135.","(","M30-39","","34",")","","19:39 min/km","3:16:36","3:16:36","","3:16:36","BG(#ebebeb)","","","B","C(#d115b8)"],["194","196","200","[img:/graphics/flags/PL.svg]","Zientara Marcin","KS ZRYW RADZIEJÓW (Bytoń)","I","200","M","","136.","(","M40-49","","47",")","","19:39 min/km","3:16:36","3:16:36","","3:16:36","","","","B","C(#d115b8)"],[200]],"DataFields":["BIB","ID","AUTORANK","COUNTRY.FLAG","CorrectSpelling([DisplayName])","[CLUB] \u0026 \" (\" \u0026 [CITY] \u0026 \")\" ","\"I\"","OverallRank","GenderMF","medal([GenderRank])","[GenderRankp]","\"(\"","[AGEGROUP1.NAME]","medal([AGRank])","if([GenderRank]\u003c=[DecorationDepth];\"OPEN\"; if([AGRank]\u003e0;[AGRank]))","\")\"","wyniki_kategorie_dodatkowe","[finish.CHIP.PACE] \u0026 \" min/km\"","Finish.CHIP","Finish.GUN","kara_text","TimeorStatus","iif([POSITION]%2;\"BG(#ebebeb)\")","if([SEX]=\"f\";\"C(#d115b8)\";)","if([SEX]=\"f\";\"C(#d115b8);B\")","if([GunRank]\u003e[GunRankDepth];\"B\";\"C(#d115b8)\")","if([GunRank]\u003c=[GunRankDepth];\"B\";\"C(#d115b8)\")"],"mid":319796,"groupFilters":[{"Type":0,"Value":"","Values":["10 km","01. Bieg Malucha (rocznik 2022 i młodsi),dystans: 50m - dziewczynki","02. Bieg Malucha (rocznik 2022 i młodsi),dystans: 50m - chłopcy","03. Roczniki 2021-2020/5-6 lat/,dystans: 100 m - dziewczynki","04. Roczniki 2021-2020/5-6 lat/,dystans: 100 m - chłopcy","05. Roczniki  2019-2017/7-9 lat/,dystans: 400 m - dziewczynki","06. Roczniki  2019-2017/7-9 lat/,dystans: 400 m - chłopcy","07. Roczniki 2016-2014/10-12 lat/,dystans:800 m - dziewczynki","08. Roczniki 2016-2014/10-12 lat/,dystans:800 m - chłopcy","09. Roczniki 2013-2010/13-16 lat/dystans: 1000 m - dziewczynki","10. Roczniki 2013-2010/13-16 lat/dystans: 1000 m - chłopcy"]},{"Type":2,"Value":"","Values":["KOBIETA","MĘŻCZYZNA"]},{"Type":2,"Value":"","Values":["","K16-19","K20-29","K30-39","K40-49","K50-59","K60-69","K70+","M16-19","M20-29","M30-39","M40-49","M50-59","M60-69","M70+"]}],"comments":{"313":1},"LiveUpdateInterval":10}